logstash_notifier/__init__.py
logstash_notifier/logger.py
supervisor_logstash_notifier-0.2.5.dist-info/METADATA
supervisor_logstash_notifier-0.2.5.dist-info/RECORD
supervisor_logstash_notifier-0.2.5.dist-info/WHEEL
supervisor_logstash_notifier-0.2.5.dist-info/entry_points.txt
supervisor_logstash_notifier-0.2.5.dist-info/top_level.txt
