Metadata-Version: 2.1
Name: supervisor-logstash-notifier
Version: 0.2.5
Summary: Stream supervisor events to a logstash instance
Home-page: https://github.com/dohop/supervisor-logstash-notifier
Author: aodj
Author-email: alexander@dohop.com
License: Apache 2.0
Platform: UNKNOWN
Requires-Dist: python-logstash (==0.4.6)
Requires-Dist: six (>=1.10.0)
Requires-Dist: argparse
